ipodnano_scrobbler/__init__.py
ipodnano_scrobbler/read_dbs.py
ipodnano_scrobbler/scrobble.py
ipodnano_scrobbler-1.2.1.dist-info/METADATA
ipodnano_scrobbler-1.2.1.dist-info/WHEEL
ipodnano_scrobbler-1.2.1.dist-info/entry_points.txt
ipodnano_scrobbler-1.2.1.dist-info/licenses/LICENSE
ipodnano_scrobbler-1.2.1.dist-info/RECORD
