Metadata-Version: 2.4
Name: ipodnano-scrobbler
Version: 1.2.1
Summary: iPod Nano 6th Gen last.fm scrobbler
License: MIT
License-File: LICENSE
Author: Your Name
Author-email: you@example.com
Requires-Python: >=3.7,<4.0
Classifier: License :: OSI Approved :: MIT License
Classifier: Programming Language :: Python :: 3
Classifier: Programming Language :: Python :: 3.7
Classifier: Programming Language :: Python :: 3.8
Classifier: Programming Language :: Python :: 3.9
Classifier: Programming Language :: Python :: 3.10
Classifier: Programming Language :: Python :: 3.11
Classifier: Programming Language :: Python :: 3.12
Classifier: Programming Language :: Python :: 3.13
Classifier: Programming Language :: Python :: 3.14
Requires-Dist: pandas
Requires-Dist: polars
Requires-Dist: pyarrow
Requires-Dist: requests
Requires-Dist: tqdm
Requires-Dist: trainerlog
